{
  "collection_path": "flujo_caja_emprestito",
  "doc_id": "26005375.0_BBVA_feb-26",
  "data": {
    "desembolso": 3635799693.0,
    "banco": "BBVA",
    "id_registro": "26005375.0_BBVA_feb-26",
    "mes": "feb-26",
    "columna_origen": "feb-26 Desembolso",
    "bp_proyecto": "26005375.0",
    "responsable": "Mauricio Jimenez",
    "fecha_procesamiento": "2025-10-20T11:50:33.082333",
    "periodo": "2026-02-01T00:00:00",
    "archivo_origen": "Matriz Emprestito.xlsx",
    "organismo": "Infraestructura",
    "descripcion_bp": "RECUPERACION DE LA INFRAESTRUCTURA VIAL DE SANTIAGO DE CALI"
  },
  "timestamp": "2025-11-09T00:48:36.739103"
}