{
  "collection_path": "flujo_caja_emprestito",
  "doc_id": "26005500.0_Banco de Occidente_dic-25",
  "data": {
    "desembolso": 5619557365.0,
    "banco": "Banco de Occidente",
    "id_registro": "26005500.0_Banco de Occidente_dic-25",
    "mes": "dic-25",
    "columna_origen": "dic-25 Desembolso",
    "bp_proyecto": "26005500.0",
    "responsable": "Esperanza Ramos",
    "fecha_procesamiento": "2025-10-20T11:50:33.076660",
    "periodo": "2025-12-01T00:00:00",
    "archivo_origen": "Matriz Emprestito.xlsx",
    "organismo": "Seguridad",
    "descripcion_bp": "Fortalecimiento a la capacidad operativa de las agencias de seguridad y justicia en Santiago de Cali"
  },
  "timestamp": "2025-11-09T00:49:23.195739"
}