{
  "collection_path": "proyecciones_emprestito",
  "doc_id": "1RbytaJ2pWpZ8xOjV39T",
  "data": {
    "nombre_banco": "POR DEFINIR",
    "nombre_organismo_reducido": "Bienes",
    "ultima_actualizacion": "2025-11-08T11:31:07.658508+00:00",
    "item": "142",
    "nombre_resumido_proceso": "Galeria Alameda (Convenio EDRU Estudios y diseños",
    "fuente": "google_sheets",
    "fecha_carga": "2025-11-08T11:31:04.580674",
    "valor_proyectado": 0,
    "nombre_generico_proyecto": "Infraestructura Social",
    "fila_origen": 142,
    "id_paa": "19676",
    "fecha_guardado": "2025-11-08T11:31:07.658508+00:00",
    "referencia_proceso": "",
    "BP": "BPX DEFINIR",
    "urlProceso": "",
    "descripcion_bp": "EJE MOTORES DE DESARROLLO"
  },
  "timestamp": "2025-11-09T00:52:15.634319"
}