{
  "collection_path": "proyecciones_emprestito",
  "doc_id": "nujmVkX3yw7gncSeQl1d",
  "data": {
    "nombre_banco": "DAVIVIENDA",
    "nombre_organismo_reducido": "Bienestar Social",
    "ultima_actualizacion": "2025-11-08T11:31:07.644667+00:00",
    "item": "84",
    "nombre_resumido_proceso": "Contrato 1: Sistema de Información del Sistema Distrital de Cuidado SIDICU",
    "fuente": "google_sheets",
    "fecha_carga": "2025-11-08T11:31:04.574180",
    "valor_proyectado": 0,
    "nombre_generico_proyecto": "Sistema Cuidarte/SIDICU",
    "fila_origen": 84,
    "id_paa": "18983",
    "fecha_guardado": "2025-11-08T11:31:07.644667+00:00",
    "referencia_proceso": "",
    "BP": "BP26005427",
    "urlProceso": "https://www.secop.gov.co/CO1BusinessLine/Tendering/ContractNoticeView/Index?prevCtxLbl=Buscar+procesos&prevCtxUrl=https%3a%2f%2fwww.secop.gov.co%3a443%2fCO1BusinessLine%2fTendering%2fContractNoticeManagement%2fIndex&notice=CO1.NTC.9023599",
    "descripcion_bp": "Fortalecimiento del Sistema Distrital de Cuidado \"Cuidarte\" en el Distrito de Santiago de Cali"
  },
  "timestamp": "2025-11-09T00:53:35.089334"
}