{
  "collection_path": "reportes_contratos",
  "doc_id": "aaECfY71H5KC2ZmmqrEV",
  "data": {
    "fecha_reporte": "2025-10-21T15:50:12.709823+00:00",
    "observaciones": "",
    "nombre_centro_gestor": "",
    "avance_fisico": 2.8,
    "url_carpeta_drive": "https://drive.google.com/drive/folders/122DxvvbhgghD5__MfsGMFPVAEe9pPsYF",
    "archivos_evidencia": [
      {
        "type": "application/vnd.openxmlformats-officedocument.wordprocessingml.document",
        "size": 13393,
        "download_url": "https://drive.google.com/uc?id=1XbN5abcPK0TnR7cxlimViIwyZ8u_CRF5",
        "url": "https://docs.google.com/document/d/1XbN5abcPK0TnR7cxlimViIwyZ8u_CRF5/edit?usp=drivesdk&ouid=107631050282737776825&rtpof=true&sd=true",
        "drive_id": "1XbN5abcPK0TnR7cxlimViIwyZ8u_CRF5",
        "status": "uploaded_successfully",
        "name": "Blanco.docx"
      }
    ],
    "referencia_contrato": "4151.010.26.1.0907-2025",
    "avance_financiero": 3.2,
    "alertas": {
      "descripcion": "",
      "es_alerta": false,
      "tipos": []
    },
    "estado_reporte": "activo"
  },
  "timestamp": "2025-11-09T01:41:39.836412"
}