{
  "collection_path": "unidades_proyecto",
  "doc_id": "UNP-974",
  "data": {
    "created_at": "2025-11-05T11:34:47.043713",
    "type": "Feature",
    "geometry": null,
    "has_geometry": false,
    "geometry_type": null,
    "properties": {
      "processed_timestamp": "2025-11-05T11:34:28.210236",
      "descripcion_intervencion": "El proyecto comprende las obras para la adecuación de la cubierta de la cancha de la\n Institución Educativa Luis Fernando Caicedo sede Principal.",
      "microtio": null,
      "bpin": "0",
      "centros_gravedad": false,
      "upid": "UNP-974",
      "nombre_up_detalle": "Principal",
      "tipo_intervencion": "Adecuaciones y mantenimientos",
      "url_proceso": null,
      "referencia_contrato": "Se genera en el 2026",
      "unidad": "UND",
      "identificador": "Presupuesto Participativo 2026",
      "tipo_equipamiento": "Institución Educativa",
      "fecha_fin": "2026",
      "estado": "En alistamiento",
      "fecha_inicio": "2026",
      "plataforma": null,
      "nombre_centro_gestor": "Secretaría de Educación",
      "avance_obra": "0.0",
      "geometry_bounds": null,
      "direccion": "Av 5A Oeste # 47 -04",
      "ano": "2026",
      "geometry_type": null,
      "dataframe": null,
      "comuna_corregimiento": "El Saladito",
      "nombre_up": "I.E. Luis Fernando Caicedo",
      "referencia_proceso": "Se genera en el 2026",
      "fuente_financiacion": "Recursos propios",
      "cantidad": "1",
      "barrio_vereda": "Montañuelas",
      "presupuesto_base": "635826336"
    },
    "updated_at": "2025-11-05T11:34:47.043713"
  },
  "timestamp": "2025-11-09T02:00:28.489858"
}