{
  "collection_path": "unidades_proyecto",
  "doc_id": "UNP-978",
  "data": {
    "created_at": "2025-11-05T11:34:47.043713",
    "type": "Feature",
    "geometry": null,
    "has_geometry": false,
    "geometry_type": null,
    "properties": {
      "processed_timestamp": "2025-11-05T11:34:28.210236",
      "descripcion_intervencion": "La intervención consiste en obras preliminares (demolición), movimiento de tierras (excavación y relleno con material seleccionado), estructuras de concreto (muros, viga y andenes, piso (baldosa y guarda escoba), revestimiento (pintura cielo y muros) y carpintería metálica exterior (malla eslabonada).",
      "microtio": null,
      "bpin": "0",
      "centros_gravedad": false,
      "upid": "UNP-978",
      "nombre_up_detalle": "Principal",
      "tipo_intervencion": "Adecuaciones y mantenimientos",
      "url_proceso": null,
      "referencia_contrato": "Se genera en el 2026",
      "unidad": "UND",
      "identificador": "Presupuesto Participativo 2026",
      "tipo_equipamiento": "Institución Educativa",
      "fecha_fin": "2026",
      "estado": "En alistamiento",
      "fecha_inicio": "2026",
      "plataforma": null,
      "nombre_centro_gestor": "Secretaría de Educación",
      "avance_obra": "0.0",
      "geometry_bounds": null,
      "direccion": "KR 22 2 65 OESTE",
      "ano": "2026",
      "geometry_type": null,
      "dataframe": null,
      "comuna_corregimiento": "COMUNA 03",
      "nombre_up": "I.E. Normal Superior Los Farallones",
      "referencia_proceso": "Se genera en el 2026",
      "fuente_financiacion": "Recursos propios",
      "cantidad": "1",
      "barrio_vereda": "Navarro - La Chanca",
      "presupuesto_base": "468175006"
    },
    "updated_at": "2025-11-05T11:34:47.043713"
  },
  "timestamp": "2025-11-09T02:00:32.015371"
}